{
  "name":"The New School",
  "slug":"The_New_School",
  "lastModified":"2020-04-03T07:09:42Z",
  "phoneNumber":"+1 212 229 5600",
  "emailAddress":"libhelp@newschool.edu",
  "contactName":"Contact Name",
  "url":"https://www.newschool.edu/",
  "type":"Institution",
  "symbols": [
    { "authority":"OCLC", "symbol":"ZMU", "priority":"a" },
    { "authority":"RESHARE", "symbol":"TNS", "priority":"a" }
  ],
  "units": [
    { "name":"List Center Library",       "slug":"TNS_LIST", "type": "Branch", "symbols": { "authority":"RESHARE", "symbol":"TNSLCL", "priority":"a" } },
    { "name":"University Center Library", "slug":"TNS_UCL",  "type": "Branch", "symbols": { "authority":"RESHARE", "symbol":"TNSUCL", "priority":"a" } },
    { "name":"Performing Arts Library",   "slug":"TNS_PAL",  "type": "Branch", "symbols": { "authority":"RESHARE", "symbol":"TNSPAL", "priority":"a" } }
  ],
  "services":[
    { 
      "slug":"The_New_School_ISO18626",
      "service":{ "name":"ReShare ISO18626 Service", "address":"https://localhost/reshare/iso18626", "type":"ISO18626", "businessFunction":"ILL" },
      "customProperties":{ "ILLPreferredNamespaces":["RESHARE", "PALCI", "IDS"] } 
    },
    {
      "slug":"The_New_School_NCIP",
      "service":{ "name":"NCIP", "address":"alephstage.library.nyu.edu:5994", "type":"NCIP", "businessFunction":"CIRC" },
      "customProperties":{ "TestParam":["Testing service account with custprop. this was failing without this prop"] }
    }
  ],
  "friends":[
    { "url":"https://raw.githubusercontent.com/openlibraryenvironment/mod-directory/master/seed_data/palci.json" },
    { "url":"https://raw.githubusercontent.com/openlibraryenvironment/mod-directory/master/seed_data/olf.json" }
  ],
  "announcements":[
    { "date":"2019-02-08", "expires":"2019-02-09", "code":"LAST_RESPORT", "description":"Due to staff sickness, please consider the Performing Arts Library a lender of last resort today, Friday 8th Feb 2019" }
  ]
}
